[
  {
    "original": "Aragorn",
    "generated": "Lostorb"
  },
  {
    "original": "Arathorn",
    "generated": "Umberdrake"
  },
  {
    "original": "Gilraen",
    "generated": "Mondhakaron"
  },
  {
    "original": "Strider",
    "generated": "Kaelfield"
  },
  {
    "original": "Elessar",
    "generated": "Hughmond"
  },
  {
    "original": "Dúnedain",
    "generated": "Paruk",
    "stems": [
      "Dunedain"
    ]
  },
  {
    "original": "Telcontar",
    "generated": "Songawar"
  },
  {
    "original": "Gondor",
    "generated": "Etherealshield"
  },
  {
    "original": "Arnor",
    "generated": "Bareth"
  },
  {
    "original": "Isildur",
    "generated": "Faith"
  },
  {
    "original": "Narsil",
    "generated": "Zaxelion"
  },
  {
    "original": "Andúril",
    "generated": "Umberwing"
  },
  {
    "original": "Ring",
    "generated": "Corithhard"
  },
  {
    "original": "hobbit",
    "generated": "Warak"
  },
  {
    "original": "Hornburg",
    "generated": "Zanewin"
  },
  {
    "original": "Return of the King",
    "generated": "Owenville"
  },
  {
    "original": "Silmarillion",
    "generated": "Celestialkey"
  },
  {
    "original": "Third Age",
    "generated": "Topaztail"
  },
  {
    "original": "Elros Tar-Minyatur",
    "generated": "Wawynorn"
  },
  {
    "original": "Andúnië",
    "generated": "Rubystorm"
  },
  {
    "original": "Elendil",
    "generated": "Taoro"
  },
  {
    "original": "Elrond",
    "generated": "Marig"
  },
  {
    "original": "Arvedui",
    "generated": "Tarcor"
  },
  {
    "original": "Fíriel",
    "generated": "Dagwood"
  },
  {
    "original": "Anárion",
    "generated": "Wispsight"
  },
  {
    "original": "Rivendell",
    "generated": "Barok"
  },
  {
    "original": "Estel",
    "generated": "Taruk"
  },
  {
    "original": "Barahir",
    "generated": "Kalorarn"
  },
  {
    "original": "Annúminas",
    "generated": "Rubymane"
  },
  {
    "original": "Arwen",
    "generated": "Jauth"
  },
  {
    "original": "Lothlórien",
    "generated": "Yaoro"
  },
  {
    "original": "Lórien",
    "generated": "Durath"
  },
  {
    "original": "Galadriel",
    "generated": "Ignisrage"
  },
  {
    "original": "Angmar",
    "generated": "Tarsilfar"
  },
  {
    "original": "Shire",
    "generated": "Durenlenheart"
  },
  {
    "original": "Thengel",
    "generated": "Cauel"
  },
  {
    "original": "Rohan",
    "generated": "Kaforoth"
  },
  {
    "original": "Ecthelion",
    "generated": "Astralblade"
  },
  {
    "original": "Thorongil",
    "generated": "Zaxelion"
  },
  {
    "original": "Eagle of the Star",
    "generated": "Yadoroth"
  },
  {
    "original": "Umbar",
    "generated": "Titantome"
  },
  {
    "original": "Cerin",
    "generated": "Lostphylactery"
  },
  {
    "original": "Amroth",
    "generated": "Hiddenblade"
  },
  {
    "original": "Ilúvatar",
    "generated": "Zaorn"
  },
  {
    "original": "Middle-earth",
    "generated": "Yorkville"
  },
  {
    "original": "Moria",
    "generated": "Xanwood"
  },
  {
    "original": "Harad",
    "generated": "Ariward"
  },
  {
    "original": "Valandil",
    "generated": "Pawin"
  },
  {
    "original": "Dúnadan",
    "generated": "Pyrebreath"
  },
  {
    "original": "Quenya",
    "generated": "Naloriel"
  },
  {
    "original": "Tarkil",
    "generated": "Rubydrake"
  },
  {
    "original": "Trotter",
    "generated": "Owennard"
  },
  {
    "original": "Sindar",
    "generated": "Xenoclaw",
    "stems": [
      "Sindarin"
    ]
  },
  {
    "original": "Padathir",
    "generated": "Infernaltome"
  },
  {
    "original": "Edhelharn",
    "generated": "Faorn"
  },
  {
    "original": "Elfstone",
    "generated": "Tarxelulf"
  },
  {
    "original": "Tolkien",
    "generated": "Duron"
  },
  {
    "original": "Peregrin",
    "generated": "Obsidianblade"
  },
  {
    "original": "Boffin",
    "generated": "Ivanwood"
  },
  {
    "original": "Bilbo",
    "generated": "Barith"
  },
  {
    "original": "Gandalf",
    "generated": "Taeth"
  },
  {
    "original": "Fosco",
    "generated": "Quinnville"
  },
  {
    "original": "Took",
    "generated": "Pareth",
    "stems": []
  },
  {
    "original": "Frodo",
    "generated": "Varoth"
  },
  {
    "original": "Sam",
    "generated": "Jaarn",
    "stems": [
      "Samwise"
    ]
  },
  {
    "original": "Gamgee",
    "generated": "Hiddentome"
  },
  {
    "original": "Rauros",
    "generated": "Lairnward"
  },
  {
    "original": "Ingold",
    "generated": "Naael"
  },
  {
    "original": "Sauron",
    "generated": "Sapphirefang"
  },
  {
    "original": "Helms",
    "generated": "Ikeaunin",
    "stems": [
      "Helm's",
      "Helm's"
    ]
  },
  {
    "original": "Dernhelm",
    "generated": "Buron"
  },
  {
    "original": "Legolas",
    "generated": "Hiddenamulet",
    "stems": [
      "Laegolas"
    ]
  },
  {
    "original": "Gimli",
    "generated": "Parik"
  },
  {
    "original": "Saruman",
    "generated": "Bertven"
  },
  {
    "original": "Edoras",
    "generated": "Tarwarnar"
  },
  {
    "original": "Théoden",
    "generated": "Ikfred"
  },
  {
    "original": "Éored",
    "generated": "Qagorath"
  },
  {
    "original": "Rohirrim",
    "generated": "Xaigrar"
  },
  {
    "original": "Isengard",
    "generated": "Faurn"
  },
  {
    "original": "Fangorn",
    "generated": "Yaren"
  },
  {
    "original": "Ent",
    "generated": "Farath",
    "stems": [
      "Ents"
    ]
  },
  {
    "original": "Éomer",
    "generated": "Umbralcore"
  },
  {
    "original": "Elladan",
    "generated": "Saukyaug"
  },
  {
    "original": "Elrohir",
    "generated": "Paulstone"
  },
  {
    "original": "Halbarad",
    "generated": "Astralmirror"
  },
  {
    "original": "Athelas",
    "generated": "Aelenaro"
  },
  {
    "original": "Glorfindel",
    "generated": "Karmicseal"
  },
  {
    "original": "Elf-lord",
    "generated": "Tauel"
  },
  {
    "original": "Nazgûl",
    "generated": "Naan"
  },
  {
    "original": "Ringwraiths",
    "generated": "Infernalcrown"
  },
  {
    "original": "Bree",
    "generated": "Ivanstone",
    "stems": [
      "Bree-lands"
    ]
  },
  {
    "original": "Weathertop",
    "generated": "Jadeamulet"
  },
  {
    "original": "Trollshaws",
    "generated": "Maeri"
  },
  {
    "original": "Bruinen",
    "generated": "Ignishorn"
  },
  {
    "original": "Boromir",
    "generated": "Glimmerfrost"
  },
  {
    "original": "Peter Jackson",
    "generated": "Vairn"
  },
  {
    "original": "Dunharrow",
    "generated": "Noblescroll"
  },
  {
    "original": "palantír",
    "generated": "Radiantseal",
    "stems": [
      "palantíri",
      "Palantir"
    ]
  },
  {
    "original": "Pelargir",
    "generated": "Losthourglass"
  },
  {
    "original": "Anduin",
    "generated": "Yarvarivan"
  },
  {
    "original": "Cair Andros",
    "generated": "Eaurn"
  },
  {
    "original": "Ithilien",
    "generated": "Buruk"
  },
  {
    "original": "Easterlings",
    "generated": "Tarith"
  },
  {
    "original": "Aranarth",
    "generated": "Taero"
  },
  {
    "original": "Midgewater Marshes",
    "generated": "Shieldvilleeth"
  },
  {
    "original": "Númenórean",
    "generated": "Onyxgrace"
  },
  {
    "original": "Tar-Minyatur",
    "generated": "Varuk"
  },
  {
    "original": "Rangers of the North",
    "generated": "Seanfield"
  },
  {
    "original": "Baggins",
    "generated": "Aldfred"
  },
  {
    "original": "Gollum",
    "generated": "Ignishorn"
  },
  {
    "original": "Rhovanion",
    "generated": "Jacorern"
  },
  {
    "original": "Thranduil",
    "generated": "Kadoruel"
  },
  {
    "original": "Mirkwood",
    "generated": "Markfred"
  },
  {
    "original": "Mordor",
    "generated": "Galenuel"
  },
  {
    "original": "Gildor",
    "generated": "Owenmond"
  },
  {
    "original": "Inglorion",
    "generated": "Kaelbert"
  },
  {
    "original": "Tom",
    "generated": "Infernalmirror"
  },
  {
    "original": "Bombadil",
    "generated": "Hughville"
  },
  {
    "original": "Barrow-downs",
    "generated": "Varag"
  },
  {
    "original": "Prancing Pony",
    "generated": "Ethfred",
    "stems": [
      "Inn of the Prancing Pony"
    ]
  },
  {
    "original": "Barliman",
    "generated": "Hiddenblade"
  },
  {
    "original": "Butterbur",
    "generated": "Taranirn"
  },
  {
    "original": "Lone-lands",
    "generated": "Unoriae"
  },
  {
    "original": "Eärendil",
    "generated": "Quantumtome"
  },
  {
    "original": "Mount Doom",
    "generated": "Paulblade",
    "stems": [
      "mountain"
    ]
  },
  {
    "original": "Cracks of Doom",
    "generated": "Wavenoro"
  },
  {
    "original": "Pippin",
    "generated": "Onyxsight"
  },
  {
    "original": "Misty Mountains",
    "generated": "Aldfred"
  },
  {
    "original": "Crebain",
    "generated": "Quinnfield"
  },
  {
    "original": "Caradhras",
    "generated": "Shieldtonsarxar"
  },
  {
    "original": "Warg",
    "generated": "Paranoro"
  },
  {
    "original": "Watcher in the Water",
    "generated": "Haorn"
  },
  {
    "original": "Mazarbul",
    "generated": "Ulfmorern"
  },
  {
    "original": "Cave-troll",
    "generated": "Oamiruel"
  },
  {
    "original": "Balrog",
    "generated": "Hiddenphylactery"
  },
  {
    "original": "Khazad-dûm",
    "generated": "Egstonehard"
  },
  {
    "original": "Anarion",
    "generated": "Umberfrost"
  },
  {
    "original": "Argonath",
    "generated": "Edbert"
  },
  {
    "original": "Parth Galen",
    "generated": "Quinnbert"
  },
  {
    "original": "Amon Hen",
    "generated": "Jaaro"
  },
  {
    "original": "Uruk",
    "generated": "Haranirn"
  },
  {
    "original": "hai",
    "generated": "Ignissight"
  },
  {
    "original": "Order of Wizards",
    "generated": "Farok"
  },
  {
    "original": "Council",
    "generated": "Bladeig",
    "stems": [
      "White Council"
    ]
  },
  {
    "original": "Gríma",
    "generated": "Markbert"
  },
  {
    "original": "Wormtongue",
    "generated": "Harddurothta"
  },
  {
    "original": "Tirith",
    "generated": "Igjackraan"
  },
  {
    "original": "Paths of the Dead",
    "generated": "Davenith"
  },
  {
    "original": "Malbeth the Seer",
    "generated": "Taron"
  },
  {
    "original": "Pelennor",
    "generated": "Washieldharpar"
  },
  {
    "original": "White Tree",
    "generated": "Fava"
  },
  {
    "original": "Denethor",
    "generated": "Pyreclaw"
  },
  {
    "original": "Éowyn",
    "generated": "Owenbert"
  },
  {
    "original": "Witch-king",
    "generated": "Lostamulet"
  },
  {
    "original": "Faramir",
    "generated": "Hughton"
  },
  {
    "original": "Ioreth",
    "generated": "Kaelmond"
  },
  {
    "original": "The hands of the King are the hands of a healer, and so shall the rightful king be known",
    "generated": "Rubydrake"
  },
  {
    "original": "Minas",
    "generated": "Kaulf"
  },
  {
    "original": "Morgul",
    "generated": "Rexblade"
  },
  {
    "original": "Black Gate",
    "generated": "Seanblade"
  },
  {
    "original": "Slag-hills",
    "generated": "Raren"
  },
  {
    "original": "Morannon",
    "generated": "Novabreath"
  },
  {
    "original": "Núrn",
    "generated": "Matometh"
  },
  {
    "original": "Númenor",
    "generated": "Mystichourglass"
  },
  {
    "original": "Fourth Age",
    "generated": "Iarava"
  },
  {
    "original": "Eldar",
    "generated": "Cedshield",
    "stems": [
      "Eldarion"
    ]
  },
  {
    "original": "Imrahil",
    "generated": "Yaroth"
  },
  {
    "original": "Gladden",
    "generated": "Primaltome"
  },
  {
    "original": "Meneldil",
    "generated": "Seanblade"
  },
  {
    "original": "Pelendur",
    "generated": "Spectralseal"
  },
  {
    "original": "Eärnil",
    "generated": "Doruth"
  },
  {
    "original": "Bill Ferny",
    "generated": "Uairn"
  },
  {
    "original": "Envinyatar",
    "generated": "Karmicamulet"
  },
  {
    "original": "Bingo",
    "generated": "Spectralscroll"
  },
  {
    "original": "B_olger",
    "generated": "Maari"
  },
  {
    "original": "Undómiel",
    "generated": "Hughstone"
  },
  {
    "original": "Padathir",
    "generated": "Zaagorikar"
  },
  {
    "original": "Rimbedir",
    "generated": "Zaneza"
  },
  {
    "original": "Balin",
    "generated": "Luminhorn"
  },
  {
    "original": "Fundin",
    "generated": "Haruk"
  },
  {
    "original": "Dwalin",
    "generated": "Nareg"
  },
  {
    "original": "Thorin",
    "generated": "Othsonlaowen"
  },
  {
    "original": "Lonely Mountain",
    "generated": "Ignisdrake"
  },
  {
    "original": "Oakenshield",
    "generated": "Quartzfrost"
  },
  {
    "original": "Erebor",
    "generated": "Durug"
  },
  {
    "original": "Smaug",
    "generated": "Heartxarith"
  },
  {
    "original": "Dunland",
    "generated": "Jadecore"
  },
  {
    "original": "Azanulbizar",
    "generated": "Darug"
  },
  {
    "original": "Thráin",
    "generated": "Xanwood"
  },
  {
    "original": "Green Dragon",
    "generated": "Xanfred"
  },
  {
    "original": "Eagle",
    "generated": "Ceded",
    "stems": [
      "Eagles"
    ]
  },
  {
    "original": "Carrock",
    "generated": "Jaael"
  },
  {
    "original": "Beorn",
    "generated": "Noblecore"
  },
  {
    "original": "Lake-town",
    "generated": "Xanfred"
  },
  {
    "original": "Roäc",
    "generated": "Galenion"
  },
  {
    "original": "Battle of Five Armies",
    "generated": "Harath"
  },
  {
    "original": "Bolg",
    "generated": "Igmondbert"
  },
  {
    "original": "Lake-men",
    "generated": "Wispdrake"
  },
  {
    "original": "TA",
    "generated": "Topazdrake"
  },
  {
    "original": "Bag End",
    "generated": "Radiantphylactery"
  },
  {
    "original": "Óin",
    "generated": "Hughheart"
  },
  {
    "original": "Ori",
    "generated": "Umbralcrown"
  },
  {
    "original": "Mithril",
    "generated": "Edward"
  },
  {
    "original": "Durin",
    "generated": "Branstone"
  },
  {
    "original": "Mirrormere",
    "generated": "Chryfrost"
  },
  {
    "original": "Mazarbul",
    "generated": "Karmicphylactery"
  },
  {
    "original": "An Unexpected Journey",
    "generated": "Igkazar"
  },
  {
    "original": "Undying Lands",
    "generated": "Dalenern"
  },
  {
    "original": "Belladonna",
    "generated": "Tarin"
  },
  {
    "original": "Glóin",
    "generated": "Haori"
  },
  {
    "original": "Trolls' lair",
    "generated": "Alranoro"
  },
  {
    "original": "Glamdring",
    "generated": "Astralamulet"
  },
  {
    "original": "Orcrist",
    "generated": "Aldward"
  },
  {
    "original": "Fíli",
    "generated": "Yorunhugh",
    "stems": [
      "Fili"
    ]
  },
  {
    "original": "Kíli",
    "generated": "Ealenaro",
    "stems": [
      "Kili"
    ]
  },
  {
    "original": "Iron Hills",
    "generated": "Facorori"
  },
  {
    "original": "Dáin",
    "generated": "Silton"
  },
  {
    "original": "Ironfoot",
    "generated": "Varon"
  },
  {
    "original": "Sackville",
    "generated": "Leoshield"
  },
  {
    "original": "Brandybuck",
    "generated": "Alsiluel"
  },
  {
    "original": "precious",
    "generated": "Fauth"
  },
  {
    "original": "Red Book of Westmarch",
    "generated": "Athwardda"
  },
  {
    "original": "Sting",
    "generated": "Jadeorb"
  },
  {
    "original": "Grey Havens",
    "generated": "Ricdorion"
  },
  {
    "original": "Valinor",
    "generated": "Qamorarn"
  },
  {
    "original": "White Tower",
    "generated": "Ionton"
  },
  {
    "original": "Osgiliath",
    "generated": "Harak"
  },
  {
    "original": "Return of the King",
    "generated": "Sapphiremane"
  },
  {
    "original": "Adrahil",
    "generated": "Warin"
  },
  {
    "original": "Finduilas",
    "generated": "Dorvillemorulf"
  },
  {
    "original": "Istar",
    "generated": "Yorkjaukstone"
  },
  {
    "original": "Imladris",
    "generated": "Forgottentome"
  },
  {
    "original": "Halfling",
    "generated": "Gregshield"
  },
  {
    "original": "Tharbad",
    "generated": "Sapphirefang"
  },
  {
    "original": "Great Horn",
    "generated": "Hairn"
  },
  {
    "original": "Drogo",
    "generated": "Mysticorb"
  },
  {
    "original": "Southrons",
    "generated": "Etherealblade"
  },
  {
    "original": "Henneth Annûn",
    "generated": "Jaeth"
  },
  {
    "original": "Anor",
    "generated": "Gorgreglorero"
  },
  {
    "original": "Noldorin",
    "generated": "Markward"
  },
  {
    "original": "Elboron",
    "generated": "Noblestaff"
  },
  {
    "original": "Emyn Arnen",
    "generated": "Topazdrake"
  },
  {
    "original": "Belecthor",
    "generated": "Mysticshield"
  },
  {
    "original": "Beregond",
    "generated": "Taern"
  },
  {
    "original": "Cirith Ungol",
    "generated": "Luminrage"
  },
  {
    "original": "Forbidden Pool",
    "generated": "Sarith"
  },
  {
    "original": "Black Wing",
    "generated": "Yareth"
  },
  {
    "original": "Shelob",
    "generated": "Ivanwin"
  },
  {
    "original": "Underhill",
    "generated": "Rubyscale"
  },
  {
    "original": "Asfaloth",
    "generated": "Glimmerstorm"
  },
  {
    "original": "Elbereth",
    "generated": "Saith"
  },
  {
    "original": "Gilthoniel",
    "generated": "Warag"
  },
  {
    "original": "Valar",
    "generated": "Divinekey"
  },
  {
    "original": "Black Rider",
    "generated": "Divinestaff"
  },
  {
    "original": "Finrod",
    "generated": "Vividwing"
  },
  {
    "original": "Emyn Muil",
    "generated": "Edna"
  },
  {
    "original": "Bamfurlong",
    "generated": "Yorkshield"
  },
  {
    "original": "Eregion",
    "generated": "Leofred"
  },
  {
    "original": "Gondorian",
    "generated": "Othuroqaced"
  },
  {
    "original": "Cormallen",
    "generated": "Lakorori"
  },
  {
    "original": "Sharkey",
    "generated": "Maron"
  },
  {
    "original": "The Dead Marsh",
    "generated": "Rarra"
  },
  {
    "original": "Meriadoc",
    "generated": "Rubygrace",
    "stems": [
      "Merry"
    ]
  },
  {
    "original": "Brandy Hal",
    "generated": "Infernaltome"
  },
  {
    "original": "Buckland",
    "generated": "Farak"
  },
  {
    "original": "Farmer Maggot",
    "generated": "Edshield"
  },
  {
    "original": "Brandywine",
    "generated": "Parun"
  },
  {
    "original": "Crickhollow",
    "generated": "Duron"
  },
  {
    "original": "Bucklebury Ferry",
    "generated": "Owenshield"
  },
  {
    "original": "Orodruin",
    "generated": "Zaneric"
  },
  {
    "original": "Landroval",
    "generated": "Edmond"
  },
  {
    "original": "Gwaihir",
    "generated": "Waforuth"
  },
  {
    "original": "Meneldor",
    "generated": "Rexnard"
  },
  {
    "original": "Bywater",
    "generated": "Umbergrace"
  },
  {
    "original": "Ruffians",
    "generated": "Paulfred"
  },
  {
    "original": "Rosie",
    "generated": "Rajoruel"
  },
  {
    "original": "Cotton",
    "generated": "Aldton"
  },
  {
    "original": "Will Whitfoot",
    "generated": "Xenofang"
  },
  {
    "original": "Elanor",
    "generated": "Zaraelxa"
  },
  {
    "original": "There and Back Again",
    "generated": "Onyxgrace"
  },
  {
    "original": "Tol",
    "generated": "Forgottentome"
  },
  {
    "original": "Eressëa",
    "generated": "Winmasar"
  },
  {
    "original": "Arda",
    "generated": "Xamoreth"
  },
  {
    "original": "Watcher",
    "generated": "Varuk",
    "stems": [
      "Two Watchers",
      "Watchers"
    ]
  },
  {
    "original": "Ñoldor",
    "generated": "Celestialamulet"
  },
  {
    "original": "Aman",
    "generated": "Xanblade"
  },
  {
    "original": "Eldamar",
    "generated": "Haarn"
  },
  {
    "original": "First Age",
    "generated": "Astralcrown"
  },
  {
    "original": "War of Wrath",
    "generated": "Nobleorb"
  },
  {
    "original": "Dagor Bragollach",
    "generated": "Yaranari"
  },
  {
    "original": "jewel",
    "generated": "Owenornowenyork",
    "stems": [
      "Great Jewels"
    ]
  },
  {
    "original": "Fëanor",
    "generated": "Vividhorn"
  },
  {
    "original": "Celeborn",
    "generated": "Gareg"
  },
  {
    "original": "Lórinand",
    "generated": "Qahorero"
  },
  {
    "original": "Nandorin",
    "generated": "Xenorage"
  },
  {
    "original": "Eriador",
    "generated": "Zalorael"
  },
  {
    "original": "Alqualondë",
    "generated": "Uthbranraruro"
  },
  {
    "original": "Celebrían",
    "generated": "Ralorael"
  },
  {
    "original": "Elven-cloaks",
    "generated": "Iaari"
  },
  {
    "original": "Gil-Orestel",
    "generated": "Primalamulet"
  },
  {
    "original": "Galadhon",
    "generated": "Celestialcore"
  },
  {
    "original": "Second Age",
    "generated": "Ekfred"
  },
  {
    "original": "Finarfin",
    "generated": "Yaarn"
  },
  {
    "original": "Eärwen",
    "generated": "Titanring"
  },
  {
    "original": "Angrod",
    "generated": "Villened"
  },
  {
    "original": "Beleriand",
    "generated": "Topazdrake"
  },
  {
    "original": "Nargothrond",
    "generated": "Karoth"
  },
  {
    "original": "Treebeard",
    "generated": "Baron"
  },
  {
    "original": "Gil-galad",
    "generated": "Varuk"
  },
  {
    "original": "Eönwë",
    "generated": "Primaltome"
  },
  {
    "original": "Melian",
    "generated": "Cedfred"
  },
  {
    "original": "Aegnor",
    "generated": "Xaran"
  },
  {
    "original": "Manwë",
    "generated": "Umbralamulet"
  },
  {
    "original": "Lindon",
    "generated": "Topazfrost"
  },
  {
    "original": "Laegil",
    "generated": "Taren"
  },
  {
    "original": "Guldur",
    "generated": "Maarn",
    "stems": [
      "Dol Guldur"
    ]
  },
  {
    "original": "Galadhrim",
    "generated": "Karmicblade"
  },
  {
    "original": "Nenya",
    "generated": "Paulblade"
  },
  {
    "original": "Uttermost West",
    "generated": "Doroth"
  },
  {
    "original": "Artanis",
    "generated": "Ramororn"
  },
  {
    "original": "Doriath",
    "generated": "Iacorirn"
  },
  {
    "original": "Thingol",
    "generated": "Talorzazane"
  },
  {
    "original": "Finwë",
    "generated": "Xenofang"
  },
  {
    "original": "Silmarils",
    "generated": "Aesonsil"
  },
  {
    "original": "Doom of Mandos",
    "generated": "Topazhorn"
  },
  {
    "original": "Nerwen",
    "generated": "Jaaro"
  },
  {
    "original": "Falmari",
    "generated": "Ignisclaw"
  },
  {
    "original": "Amazon",
    "generated": "Marith"
  },
  {
    "original": "Trees",
    "generated": "Karmicmirror",
    "stems": [
      "Three Trees",
      "Two Trees"
    ]
  },
  {
    "original": "Menegroth",
    "generated": "Pyrewing"
  },
  {
    "original": "King Elu",
    "generated": "Quinnric"
  },
  {
    "original": "Narog",
    "generated": "Forgottentome"
  },
  {
    "original": "Telerian",
    "generated": "Zaneward"
  },
  {
    "original": "Losgar",
    "generated": "Othka"
  },
  {
    "original": "Yavanna",
    "generated": "Glimmermane"
  },
  {
    "original": "Celebrimbor",
    "generated": "Gaath"
  },
  {
    "original": "Ost-in-Edhil",
    "generated": "Akfredyork"
  },
  {
    "original": "Aldarion",
    "generated": "Burath"
  },
  {
    "original": "Elven-smith",
    "generated": "Obsidianmirror"
  },
  {
    "original": "Gwaith-i-Mírdain",
    "generated": "Dagbert"
  },
  {
    "original": "Ulmo",
    "generated": "Glimmerwing"
  },
  {
    "original": "Belfalas",
    "generated": "Karak"
  },
  {
    "original": "Rhovanion",
    "generated": "Topazclaw"
  },
  {
    "original": "Círdan",
    "generated": "Radiantamulet"
  },
  {
    "original": "Silvan",
    "generated": "Gamorion",
    "stems": [
      "Silvan Elves"
    ]
  },
  {
    "original": "Eorl",
    "generated": "Forgottenhourglass"
  },
  {
    "original": "Battle of the Field of Celebrant",
    "generated": "Faith"
  },
  {
    "original": "lembas",
    "generated": "Divinecrown"
  },
  {
    "original": "Mallorn",
    "generated": "Xanfa"
  },
  {
    "original": "Celebdil",
    "generated": "Macoruro"
  },
  {
    "original": "Barad-dûr",
    "generated": "Yorkville"
  },
  {
    "original": "Envinyanta",
    "generated": "Orneth"
  },
  {
    "original": "Mithlond",
    "generated": "Lumingrace"
  },
  {
    "original": "Olórin",
    "generated": "Wauel",
    "stems": [
      "Olorion"
    ]
  },
  {
    "original": "Maiar",
    "generated": "Mysticmirror"
  },
  {
    "original": "Ainur",
    "generated": "Durek"
  },
  {
    "original": "Varda",
    "generated": "Ivanbert"
  },
  {
    "original": "Irmo",
    "generated": "Obsidianseal"
  },
  {
    "original": "Mithrandir",
    "generated": "Leofred"
  },
  {
    "original": "Tharkûn",
    "generated": "Alleneth"
  },
  {
    "original": "Holman",
    "generated": "Embertail"
  },
  {
    "original": "Troll",
    "generated": "Harug"
  },
  {
    "original": "Goblin",
    "generated": "Jackward"
  },
  {
    "original": "Nienna",
    "generated": "Farag"
  },
  {
    "original": "Necromancer",
    "generated": "Ulfton"
  },
  {
    "original": "Incánus",
    "generated": "Tarek"
  },
  {
    "original": "Dvergatal",
    "generated": "Hiddenshield"
  },
  {
    "original": "Dale",
    "generated": "Naxeleri"
  },
  {
    "original": "Ered Luin",
    "generated": "Hiddenmirror"
  },
  {
    "original": "White Rider",
    "generated": "Forgottenorb"
  },
  {
    "original": "Two Towers",
    "generated": "Vairn"
  },
  {
    "original": "Black Speech",
    "generated": "Gregforblade"
  },
  {
    "original": "Radagast",
    "generated": "Sarun"
  },
  {
    "original": "Orthanc",
    "generated": "Ueldarbororo"
  },
  {
    "original": "Shadowfax",
    "generated": "Celestialorb"
  },
  {
    "original": "Redhorn Pass",
    "generated": "Eaxelorn"
  },
  {
    "original": "You cannot pass",
    "generated": "Raroth"
  },
  {
    "original": "I am a servant of the Secret Fire",
    "generated": "Celestialtome"
  },
  {
    "original": "Udûn",
    "generated": "Obsidianamulet"
  },
  {
    "original": "Morgoth",
    "generated": "Yarsasonton"
  },
  {
    "original": "Zirakzigil",
    "generated": "Fredikokmark"
  },
  {
    "original": "Eru",
    "generated": "Vanorion"
  },
  {
    "original": "Caras",
    "generated": "Luminbreath"
  },
  {
    "original": "Three Hunters",
    "generated": "Rexfred"
  },
  {
    "original": "Westfold",
    "generated": "Vividrage"
  },
  {
    "original": "Huorns",
    "generated": "Umbralamulet"
  },
  {
    "original": "Seeing Stone",
    "generated": "Vividfire"
  },
  {
    "original": "Grond",
    "generated": "Emberfrost"
  },
  {
    "original": "Barrow-blade",
    "generated": "Yorkward"
  },
  {
    "original": "Towers of the Teeth",
    "generated": "Maaro"
  },
  {
    "original": "Mindolluin",
    "generated": "Karath"
  },
  {
    "original": "Narya",
    "generated": "Tomfred"
  },
  {
    "original": "Sméagol",
    "generated": "Infernalblade",
    "stems": [
      "smay-ah-gol"
    ]
  },
  {
    "original": "Trahald",
    "generated": "Agquinn"
  },
  {
    "original": "Stoor",
    "generated": "Gaithulfiel"
  },
  {
    "original": "Déagol",
    "generated": "Emberrage"
  },
  {
    "original": "Gladden Fields",
    "generated": "Bureg"
  },
  {
    "original": "riddle-game",
    "generated": "Ignismane"
  },
  {
    "original": "What have I got in my pocket",
    "generated": "Iaael"
  },
  {
    "original": "Nen Hithoel",
    "generated": "Ivanblade"
  },
  {
    "original": "Ephel Dúath",
    "generated": "Haraelae"
  },
  {
    "original": "Ungoliant",
    "generated": "Jaiel"
  },
  {
    "original": "Torech Ungol",
    "generated": "Ignishorn"
  },
  {
    "original": "Gorbag",
    "generated": "Mondranurnbran"
  },
  {
    "original": "Shagrat",
    "generated": "Barog"
  },
  {
    "original": "Nine Riders",
    "generated": "Paulson"
  },
  {
    "original": "Nine Walkers",
    "generated": "Voidamulet"
  },
  {
    "original": "Arod",
    "generated": "Saori"
  },
  {
    "original": "Glittering Caves",
    "generated": "Vividwing"
  },
  {
    "original": "Bill the Pony",
    "generated": "Mysticstaff"
  },
  {
    "original": "J.R.R.",
    "generated": "Aldfield"
  },
  {
    "original": "Gondolin",
    "generated": "Infernalphylactery"
  },
  {
    "original": "Thrór",
    "generated": "Quinnfred"
  },
  {
    "original": "Allen & Unwin",
    "generated": "Novawing"
  },
  {
    "original": "Nori",
    "generated": "Iauro"
  },
  {
    "original": "Dori",
    "generated": "Aldwin"
  },
  {
    "original": "Bifur",
    "generated": "Ignisbreath"
  },
  {
    "original": "Bofur",
    "generated": "Primalmirror"
  },
  {
    "original": "Bombur",
    "generated": "Norvar"
  },
  {
    "original": "Arkenstone",
    "generated": "Gavillenaari"
  },
  {
    "original": "Baran",
    "generated": "Urnuthalen"
  },
  {
    "original": "Ghân-buri-Ghân",
    "generated": "Lostblade"
  },
  {
    "original": "Rhûn",
    "generated": "Caorn"
  },
  {
    "original": "Drúadan",
    "generated": "Vividtail"
  },
  {
    "original": "Causeway Forts",
    "generated": "Hiddenseal"
  },
  {
    "original": "Houses of Healing",
    "generated": "Iadorion"
  },
  {
    "original": "Erkenbrand",
    "generated": "Villevaulfjor"
  },
  {
    "original": "Uglúk",
    "generated": "Markfred"
  },
  {
    "original": "Grishnákh",
    "generated": "Cadoreth"
  },
  {
    "original": "Quickbeam",
    "generated": "Viknard"
  },
  {
    "original": "Oliphaunt",
    "generated": "Hughson"
  },
  {
    "original": "Dead Marshes",
    "generated": "Aelorarn"
  },
  {
    "original": "Fingolfin",
    "generated": "Umbergrace"
  },
  {
    "original": "Primula",
    "generated": "Rarun"
  },
  {
    "original": "Helcaraxë",
    "generated": "Waarn"
  }
]